gans_package/__init__.py
gans_package/Loss_F/__init__.py
gans_package/Loss_F/loss.py
gans_package/data/__init__.py
gans_package/data/cityscape.py
gans_package/dataloader/__init__.py
gans_package/dataloader/cityscape.py
gans_package/models/C_VAE.py
gans_package/models/DCGAN.py
gans_package/models/GAN.py
gans_package/models/Pix2PixHD.py
gans_package/models/SNGAN.py
gans_package/models/SRGAN.py
gans_package/models/StyleGAN.py
gans_package/models/__init__.py
gans_package/utils/__init__.py
gans_package/utils/model.py
gans_package/utils/train.py
gans_implementations-0.1.0.dist-info/LICENSE
gans_implementations-0.1.0.dist-info/METADATA
gans_implementations-0.1.0.dist-info/WHEEL
gans_implementations-0.1.0.dist-info/top_level.txt
gans_implementations-0.1.0.dist-info/RECORD
