Metadata-Version: 2.1
Name: gans-implementations
Version: 0.1.0
Summary: A bunch of GAN implementations
Home-page: https://github.com/UdbhavPrasad072300/GANs-Implementations
Author: Udbhav Prasad
Author-email: udbhavprasad072300@gmail.com
License: MIT
Platform: UNKNOWN
Classifier: Development Status :: 3 - Alpha
Classifier: Intended Audience :: Science/Research
Classifier: Operating System :: OS Independent
Classifier: License :: OSI Approved :: MIT License
Classifier: Topic :: Scientific/Engineering :: Artificial Intelligence
Classifier: Programming Language :: Python :: 3 :: Only
